meteopy/__init__.py
meteopy/settings.py
meteopy/viewer.py
meteopy-1.3.dist-info/METADATA
meteopy-1.3.dist-info/WHEEL
meteopy-1.3.dist-info/top_level.txt
meteopy-1.3.dist-info/RECORD
