Metadata-Version: 2.1
Name: meteopy
Version: 1.3
Summary: Code for MeteoPy project (demo project)
Home-page: https://git.meteo.fr/deep_learning/demo-projet-python
Author: LabIA-MF
Author-email: lab_ia@meteo.fr
License: UNKNOWN
Platform: UNKNOWN
